mmcci/CCIData_class.py
mmcci/__init__.py
mmcci/an.py
mmcci/io.py
mmcci/it.py
mmcci/pl.py
mmcci/plot_helper.py
mmcci/sc.py
mmcci/tl.py
mmcci/data/__init__.py
mmcci/data/connectomeDB2020_lit.txt
mmcci-1.0.8.dist-info/licenses/LICENSE.txt
mmcci-1.0.8.dist-info/METADATA
mmcci-1.0.8.dist-info/WHEEL
mmcci-1.0.8.dist-info/top_level.txt
mmcci-1.0.8.dist-info/RECORD
