Metadata-Version: 2.4
Name: mmcci
Version: 1.0.8
Summary: A Python package for processing multi-platform, multi-sample CCI data
Home-page: https://github.com/GenomicsMachineLearning/MMCCI
Author: Genomics and Machine Learning lab
Author-email: l.hockey@uq.edu.au
Project-URL: Bug Tracker, https://github.com/GenomicsMachineLearning/MMCCI/issues
Project-URL: repository, https://github.com/GenomicsMachineLearning/MMCCI
Classifier: Programming Language :: Python :: 3
Classifier: License :: OSI Approved :: MIT License
Classifier: Operating System :: OS Independent
Requires-Python: >=3.9
License-File: LICENSE.txt
Requires-Dist: numpy<2.0.0,>=1.24.0
Requires-Dist: pandas>=2.1.4
Requires-Dist: networkx>=3.3.0
Requires-Dist: matplotlib<4.0.0,>=3.8.2
Requires-Dist: scikit-learn>=1.3.0
Requires-Dist: scipy>=1.9.1
Requires-Dist: tqdm>=4.66.1
Requires-Dist: gseapy<1.1.7,>=1.1.1
Requires-Dist: scanpy>=1.9.0
Requires-Dist: seaborn>=0.11.2
Requires-Dist: anndata<=0.10.8
Dynamic: license-file
